ssmecs/__init__.py
ssmecs/ssm_ecs.py
ssm_ecs-0.6.dist-info/LICENSE
ssm_ecs-0.6.dist-info/METADATA
ssm_ecs-0.6.dist-info/WHEEL
ssm_ecs-0.6.dist-info/entry_points.txt
ssm_ecs-0.6.dist-info/top_level.txt
ssm_ecs-0.6.dist-info/RECORD
