Metadata-Version: 2.1
Name: ssm-ecs
Version: 0.6
Summary: ssm-ecs
Home-page: https://github.com/umzegher/ssm-ecs
Author: Ben Zeghers
License: MIT
Keywords: amazon aws ssm ecs
Platform: UNKNOWN
Classifier: Development Status :: 3 - Alpha
Classifier: License :: OSI Approved :: MIT License
Classifier: Environment :: Console
Requires-Dist: boto3
